loggingex/__init__.py
loggingex/_version.py
loggingex/exceptions.py
loggingex/context/__init__.py
loggingex/context/change.py
loggingex/context/exceptions.py
loggingex/context/filter.py
loggingex/context/shortcuts.py
loggingex/context/store.py
loggingex/wsgi/__init__.py
loggingex/wsgi/request_context.py
loggingex/wsgi/util.py
loggingex-1.2.0.dist-info/LICENSE
loggingex-1.2.0.dist-info/METADATA
loggingex-1.2.0.dist-info/WHEEL
loggingex-1.2.0.dist-info/top_level.txt
loggingex-1.2.0.dist-info/RECORD
