Metadata-Version: 2.1
Name: loggingex
Version: 1.2.0
Summary: Logging Extensions
Home-page: https://github.com/open-things/loggingex/
Author: Paulius Maruška
Author-email: paulius.maruska+loggingex@gmail.com
License: MIT
Platform: UNKNOWN
Classifier: Development Status :: 5 - Production/Stable
Classifier: Intended Audience :: Developers
Classifier: License :: OSI Approved :: MIT License
Classifier: Operating System :: OS Independent
Classifier: Operating System :: MacOS :: MacOS X
Classifier: Operating System :: Microsoft :: Windows
Classifier: Operating System :: POSIX
Classifier: Programming Language :: Python :: 3
Classifier: Programming Language :: Python :: 3.5
Classifier: Programming Language :: Python :: 3.6
Classifier: Programming Language :: Python :: 3.7
Classifier: Programming Language :: Python :: 3 :: Only
Classifier: Topic :: Software Development :: Libraries
Classifier: Topic :: System :: Logging
Requires-Python: >=3.5
Requires-Dist: contextvars ; python_version < "3.7"
